MANIFEST.in
README.rst
setup.py
test.py
masala/__init__.py
masala/logging.py
masala/match.py
masala/perhaps.py
masala/shorthand.py
masala/utils.py
masala.egg-info/PKG-INFO
masala.egg-info/SOURCES.txt
masala.egg-info/dependency_links.txt
masala.egg-info/requires.txt
masala.egg-info/top_level.txt
masala/datatype/__init__.py
masala/datatype/base.py
masala/datatype/result.py
masala/datatype/stream/__init__.py
masala/datatype/stream/error.py
masala/datatype/stream/itertools_ext.py
masala/datatype/stream/linq_ext.py
masala/datatype/stream/stream.py