Metadata-Version: 1.1
Name: masala
Version: 0.0.2
Summary: curry functional patternpatch linq
Home-page: https://github.com/hachibeeDI/masala
Author: OGURA_Daiki
Author-email: 8hachibee125@gmail.com
License: MIT
Platform: UNKNOWN
Classifier: Programming Language :: Python
Classifier: Development Status :: 4 - Beta
Classifier: License :: OSI Approved :: MIT License
Classifier: Programming Language :: Python :: 2
Classifier: Programming Language :: Python :: 2.7
Classifier: Programming Language :: Python :: 3
Classifier: Programming Language :: Python :: 3.4
Classifier: Topic :: Software Development :: Libraries :: Python Modules
Classifier: Topic :: Utilities
